lack/__init__.py
lack/logger.py
lack/logger_interface.py
lack/logger_manager.py
logging_release-0.0.4.dist-info/LICENSE
logging_release-0.0.4.dist-info/WHEEL
logging_release-0.0.4.dist-info/METADATA
logging_release-0.0.4.dist-info/RECORD
