Metadata-Version: 2.1
Name: logging-release
Version: 0.0.4
Summary: __init__ module exports main interfaces that developers of dynamo series packages use. The detailed implementation is based on python logging module with customized wrapper classes.
Author-email: "Ke Ni, Xiaojie Qiu, Yan Zhang" <dummtindex@gmail.com>
